requirements.txt
aide/__init__.py
aide/agent.py
aide/interpreter.py
aide/journal.py
aide/journal2report.py
aide/run.py
aide/backend/__init__.py
aide/backend/backend_anthropic.py
aide/backend/backend_gemini.py
aide/backend/backend_openai.py
aide/backend/backend_openrouter.py
aide/backend/utils.py
aide/example_tasks/bitcoin_price.md
aide/example_tasks/house_prices.md
aide/example_tasks/bitcoin_price/BTC-USD.csv
aide/example_tasks/house_prices/data_description.txt
aide/example_tasks/house_prices/sample_submission.csv
aide/example_tasks/house_prices/test.csv
aide/example_tasks/house_prices/train.csv
aide/utils/__init__.py
aide/utils/config.py
aide/utils/config.yaml
aide/utils/data_preview.py
aide/utils/metric.py
aide/utils/response.py
aide/utils/serialize.py
aide/utils/tree_export.py
aide/utils/viz_templates/template.html
aide/utils/viz_templates/template.js
aide/webui/__init__.py
aide/webui/app.py
aideml-0.2.2.dist-info/licenses/LICENSE
aideml-0.2.2.dist-info/METADATA
aideml-0.2.2.dist-info/WHEEL
aideml-0.2.2.dist-info/entry_points.txt
aideml-0.2.2.dist-info/top_level.txt
aideml-0.2.2.dist-info/RECORD
