Metadata-Version: 2.4
Name: aideml
Version: 0.2.2
Summary: Autonomous AI for Data Science and Machine Learning
Home-page: https://github.com/Wecoai/aideml
Author: Weco AI
Author-email: contact@weco.ai
Classifier: Programming Language :: Python :: 3
Classifier: Operating System :: OS Independent
Classifier: Topic :: Scientific/Engineering :: Artificial Intelligence
Requires-Python: >=3.10
License-File: LICENSE
Requires-Dist: black==24.3.0
Requires-Dist: funcy==2.0
Requires-Dist: humanize==4.8.0
Requires-Dist: jsonschema==4.19.2
Requires-Dist: numpy==1.26.2
Requires-Dist: openai>=1.69.0
Requires-Dist: anthropic>=0.20.0
Requires-Dist: pandas==2.1.4
Requires-Dist: pytest==7.4.3
Requires-Dist: requests>=2.32.4
Requires-Dist: scikit-learn==1.5.0
Requires-Dist: rich==13.7.0
Requires-Dist: scipy==1.11.4
Requires-Dist: dataclasses_json>=0.6.4
Requires-Dist: omegaconf>=2.3.0
Requires-Dist: loguru==0.7.2
Requires-Dist: shutup>=0.2.0
Requires-Dist: tqdm==4.66.3
Requires-Dist: coolname>=2.2.0
Requires-Dist: igraph>=0.11.3
Requires-Dist: genson>=1.2.0
Requires-Dist: torch
Requires-Dist: torchvision
Requires-Dist: torchaudio
Requires-Dist: torchtext
Requires-Dist: lightgbm
Requires-Dist: matplotlib
Requires-Dist: seaborn
Requires-Dist: gensim
Requires-Dist: scikit-image
Requires-Dist: opencv-python
Requires-Dist: scipy
Requires-Dist: scikit-learn
Requires-Dist: biopython
Requires-Dist: imbalanced-learn
Requires-Dist: h5py
Requires-Dist: biopython
Requires-Dist: numba
Requires-Dist: arrow
Requires-Dist: markovify
Requires-Dist: imgaug
Requires-Dist: scikit-optimize
Requires-Dist: plotly
Requires-Dist: hyperopt
Requires-Dist: bayesian-optimization
Requires-Dist: imagecodecs
Requires-Dist: hmmlearn
Requires-Dist: bayespy==0.5.1
Requires-Dist: sklearn-pandas
Requires-Dist: tensorpack
Requires-Dist: sentencepiece
Requires-Dist: librosa
Requires-Dist: ipykernel
Requires-Dist: ipython
Requires-Dist: nbformat
Requires-Dist: kornia
Requires-Dist: Pillow
Requires-Dist: pyparsing
Requires-Dist: pytz
Requires-Dist: PyYAML
Requires-Dist: tqdm
Requires-Dist: fastai
Requires-Dist: gym
Requires-Dist: optuna
Requires-Dist: transformers
Requires-Dist: datasets==2.1.0
Requires-Dist: torchmetrics
Requires-Dist: pytorch-lightning
Requires-Dist: sympy
Requires-Dist: timm
Requires-Dist: torchinfo
Requires-Dist: pdf2image
Requires-Dist: PyPDF
Requires-Dist: pyocr
Requires-Dist: pyarrow
Requires-Dist: xlrd
Requires-Dist: backoff
Requires-Dist: streamlit==1.40.2
Requires-Dist: python-dotenv
Dynamic: author
Dynamic: author-email
Dynamic: classifier
Dynamic: description
Dynamic: description-content-type
Dynamic: home-page
Dynamic: license-file
Dynamic: requires-dist
Dynamic: requires-python
Dynamic: summary
